{
    "name": "1Pass",
    "slug": "1pass",
    "version": "1.1.5",
    "author": "<a href=\"https://1pass.me\">1Pass</a>",
    "author_profile": "https://profiles.wordpress.org/duncanjbrown/",
    "contributors": {
        "duncanjbrown": {
            "profile": "https://profiles.wordpress.org/duncanjbrown/",
            "avatar": "https://secure.gravatar.com/avatar/fcf92655f8cf9f885e784119dc6086da?s=96&d=monsterid&r=g",
            "display_name": "duncanjbrown"
        }
    },
    "requires": "4.0",
    "tested": "4.4.33",
    "requires_php": false,
    "requires_plugins": [],
    "compatibility": [],
    "rating": 100,
    "ratings": {
        "5": 1,
        "4": 0,
        "3": 0,
        "2": 0,
        "1": 0
    },
    "num_ratings": 1,
    "support_url": "https://wordpress.org/support/plugin/1pass/",
    "support_threads": 0,
    "support_threads_resolved": 0,
    "active_installs": 0,
    "downloaded": 1494,
    "last_updated": "2016-04-18 12:24:00",
    "added": "2015-11-18",
    "homepage": "",
    "sections": {
        "description": "<p><a href=\"https://1pass.me\" rel=\"nofollow ugc\">1Pass</a> is a simple and robust plug-in for selling digital content instantly from your WordPress site.</p>\n<p>The 1Pass plugin allows you to place “buy” buttons anywhere on your posts and pages.</p>\n<p>You receive 70% of gross sales revenues via PayPal.</p>\n<p>1Pass retains 30% of gross sales revenues, out of which we pay all transaction costs and applicable taxes. There are no other charges or fees for using 1Pass.</p>\n<p>You can track your sales in real time on your 1Pass publisher dashboard.</p>\n<p>To start taking money you need a free API key from our website: <a href=\"https://1pass.me/publisher-signup\" rel=\"nofollow ugc\">https://1pass.me/publisher-signup</a></p>\n<p>More documentation here: <a href=\"https://1pass.me/1pass-for-wordpress\" rel=\"nofollow ugc\">https://1pass.me/1pass-for-wordpress</a></p>\n<p>Email questions: support@1pass.me.</p>\n<p>Custom support available for large and complex sites: duncan@1pass.me.</p>\n",
        "installation": "<ol>\n<li>Upload the <code>/1pass-for-wordpress</code> folder to the <code>wp-content/plugins</code> directory</li>\n<li>Activate</li>\n<li>Add your API keys to the 1Pass settings page. Get keys from <a href=\"https://1pass.me\" rel=\"nofollow ugc\">https://1pass.me</a>.</li>\n</ol>\n",
        "changelog": "<h4>1.1.5</h4>\n<p>Update documentation. Add 1Pass as an author.</p>\n<h4>1.1.4</h4>\n<p>Ensure GUIDs are always html-decoded by the time they appear in the feed or on the page. Workaround for https://core.trac.wordpress.org/ticket/24248.</p>\n<h4>1.1.3</h4>\n<p>Custom Post Types were not appearing in the Atom feed. They do now.</p>\n<h4>1.1.2</h4>\n<p>Easy configuration. Copy and paste your API keys into the plugin with a couple of clicks.</p>\n<h4>1.1.1</h4>\n<p>Fix bug where 1Pass was not automatically enabled</p>\n<h4>1.1.0</h4>\n<p>Remodel settings page Use &#8216;Read More&#8217; instead of the <code>[1pass]</code> shortcode Fix issue with WooCommerce</p>\n<h4>1.0.3</h4>\n<p>Fix issue with conflicting README.md and readme.txt</p>\n<h4>1.0.1</h4>\n<p>Depend on the <a href=\"https://github.com/1Pass/1pass-common\" rel=\"nofollow ugc\">1Pass-Common PHP library</a></p>\n<h4>0.3</h4>\n<ul>\n<li>Add custom Atom template</li>\n</ul>\n<h4>0.2</h4>\n<ul>\n<li>Add demo mode</li>\n</ul>\n<h4>0.1</h4>\n<ul>\n<li>Initial release</li>\n</ul>\n"
    },
    "short_description": "Sell articles from any WordPress website instantly",
    "description": "<p><a href=\"https://1pass.me\" rel=\"nofollow ugc\">1Pass</a> is a simple and robust plug-in for selling digital content instantly from your WordPress site.</p>\n<p>The 1Pass plugin allows you to place “buy” buttons anywhere on your posts and pages.</p>\n<p>You receive 70% of gross sales revenues via PayPal.</p>\n<p>1Pass retains 30% of gross sales revenues, out of which we pay all transaction costs and applicable taxes. There are no other charges or fees for using 1Pass.</p>\n<p>You can track your sales in real time on your 1Pass publisher dashboard.</p>\n<p>To start taking money you need a free API key from our website: <a href=\"https://1pass.me/publisher-signup\" rel=\"nofollow ugc\">https://1pass.me/publisher-signup</a></p>\n<p>More documentation here: <a href=\"https://1pass.me/1pass-for-wordpress\" rel=\"nofollow ugc\">https://1pass.me/1pass-for-wordpress</a></p>\n<p>Email questions: support@1pass.me.</p>\n<p>Custom support available for large and complex sites: duncan@1pass.me.</p>\n",
    "download_link": "https://downloads.wordpress.org/plugin/1pass.1.1.5.zip",
    "upgrade_notice": [],
    "screenshots": [
        {
            "src": "https://ps.w.org/1pass/assets/screenshot-1.png?rev=1288658",
            "caption": "The 1Pass button in situ on an article page"
        },
        {
            "src": "https://ps.w.org/1pass/assets/screenshot-2.png?rev=1288658",
            "caption": "A user tops up their account on the 1Pass service"
        },
        {
            "src": "https://ps.w.org/1pass/assets/screenshot-3.png?rev=1288658",
            "caption": "The 1Pass settings page"
        }
    ],
    "tags": {
        "paywalls": "paywalls",
        "single-article-sales": "single-article-sales"
    },
    "stable_tag": "1.1.5",
    "versions": {
        "0.1": "https://downloads.wordpress.org/plugin/1pass.0.1.zip",
        "0.2": "https://downloads.wordpress.org/plugin/1pass.0.2.zip",
        "0.3": "https://downloads.wordpress.org/plugin/1pass.0.3.zip",
        "1.0": "https://downloads.wordpress.org/plugin/1pass.1.0.zip",
        "1.0.1": "https://downloads.wordpress.org/plugin/1pass.1.0.1.zip",
        "1.0.2": "https://downloads.wordpress.org/plugin/1pass.1.0.2.zip",
        "1.0.3": "https://downloads.wordpress.org/plugin/1pass.1.0.3.zip",
        "1.1.0": "https://downloads.wordpress.org/plugin/1pass.1.1.0.zip",
        "1.1.1": "https://downloads.wordpress.org/plugin/1pass.1.1.1.zip",
        "1.1.2": "https://downloads.wordpress.org/plugin/1pass.1.1.2.zip",
        "1.1.3": "https://downloads.wordpress.org/plugin/1pass.1.1.3.zip",
        "1.1.4": "https://downloads.wordpress.org/plugin/1pass.1.1.4.zip",
        "1.1.5": "https://downloads.wordpress.org/plugin/1pass.1.1.5.zip",
        "trunk": "https://downloads.wordpress.org/plugin/1pass.zip"
    },
    "business_model": false,
    "repository_url": "",
    "commercial_support_url": "",
    "donate_link": "",
    "banners": {
        "low": "https://ps.w.org/1pass/assets/banner-772x250.png?rev=1288658",
        "high": "https://ps.w.org/1pass/assets/banner-1544x500.png?rev=1288658"
    },
    "icons": {
        "1x": "https://ps.w.org/1pass/assets/icon-128x128.png?rev=1288658",
        "2x": "https://ps.w.org/1pass/assets/icon-256x256.png?rev=1288658"
    },
    "blocks": [],
    "block_assets": [],
    "author_block_count": 0,
    "author_block_rating": 100,
    "blueprints": [],
    "preview_link": "",
    "language_packs": []
}