{
    "name": "Bangla Converter (Bijoy To Unicode, Unicode To Bijoy)",
    "slug": "bangla-converter",
    "version": "1.1.0",
    "author": "<a href=\"https://synthasoft.com/\">SynthiaSoft</a>",
    "author_profile": "https://profiles.wordpress.org/rashedulhaquerumi/",
    "contributors": {
        "rashedulhaquerumi": {
            "profile": "https://profiles.wordpress.org/rashedulhaquerumi/",
            "avatar": "https://secure.gravatar.com/avatar/f6828697685f163b08169acbe3f75eac?s=96&d=monsterid&r=g",
            "display_name": "Rashedul Haque Rumi"
        },
        "synthiasoft": {
            "profile": "https://profiles.wordpress.org/synthiasoft/",
            "avatar": "https://secure.gravatar.com/avatar/b76f3093218b4f1b64966ce0d655169f?s=96&d=monsterid&r=g",
            "display_name": "Synthia Soft"
        }
    },
    "requires": "5.1",
    "tested": "6.0.9",
    "requires_php": "7.1",
    "requires_plugins": [],
    "compatibility": [],
    "rating": 20,
    "ratings": {
        "5": 0,
        "4": 0,
        "3": 0,
        "2": 0,
        "1": 1
    },
    "num_ratings": 1,
    "support_url": "https://wordpress.org/support/plugin/bangla-converter/",
    "support_threads": 0,
    "support_threads_resolved": 0,
    "active_installs": 30,
    "downloaded": 977,
    "last_updated": "2022-10-15 11:53pm GMT",
    "added": "2022-10-15",
    "homepage": "https://rumi.pro/bangla-converter",
    "sections": {
        "description": "<p>This converter will help you to convert your bangla bijoy Ascii text to convert Unicode text or Unicode text to convert bijoy Ascii text. Even with single click you can correct broken words. You can get help from it to develop your bangla web page or write bangla language any anywher in webpage. Also you can write bangla text using unicode editor box without installing any thirdparty software.</p>\n",
        "installation": "<ol>\n<li>Download The Plugin</li>\n<li>\n<p>Upload the plugin files to the <code>/wp-content/plugins/bangla-converter</code> directory, or install the plugin through the WordPress plugins screen directly.</p>\n</li>\n<li>\n<p>Activate the plugin through the &#8216;Plugins&#8217; screen in WordPress.</p>\n</li>\n<li>goto https://yourwebsite.com/converter/ to use this converter.</li>\n</ol>\n",
        "faq": "\n<dt id='is%20this%20plugin%20will%20work%20with%20any%20theme'>\nIs this plugin will work with any Theme\n</h4>\n<p>\n<p>Yes, You can use this plugin with any WordPress theme.</p>\n</p>\n\n"
    },
    "short_description": "This converter will help you to convert your bangla bijoy Ascii text to convert Unicode text or Unicode text to convert bijoy Ascii text",
    "description": "<p>This converter will help you to convert your bangla bijoy Ascii text to convert Unicode text or Unicode text to convert bijoy Ascii text. Even with single click you can correct broken words. You can get help from it to develop your bangla web page or write bangla language any anywher in webpage. Also you can write bangla text using unicode editor box without installing any thirdparty software.</p>\n",
    "download_link": "https://downloads.wordpress.org/plugin/bangla-converter.zip",
    "upgrade_notice": [],
    "screenshots": [
        {
            "src": "https://ps.w.org/bangla-converter/assets/screenshot-1.png?rev=2799447",
            "caption": ""
        }
    ],
    "tags": {
        "bangla": "bangla",
        "bangla-blog": "Bangla Blog",
        "bangla-font": "Bangla Font",
        "font": "font",
        "news": "news"
    },
    "stable_tag": "trunk",
    "versions": {
        "1.0.0-beta": "https://downloads.wordpress.org/plugin/bangla-converter.1.0.0-beta.zip"
    },
    "business_model": false,
    "repository_url": "",
    "commercial_support_url": "",
    "donate_link": "https://rumi.pro/donate/",
    "banners": {
        "low": "https://ps.w.org/bangla-converter/assets/banner-772x250.png?rev=2799446",
        "high": false
    },
    "icons": {
        "1x": "https://ps.w.org/bangla-converter/assets/icon-128x128.png?rev=2799442"
    },
    "blocks": [],
    "block_assets": [],
    "author_block_count": 0,
    "author_block_rating": 20,
    "blueprints": [],
    "preview_link": "",
    "language_packs": []
}