{
    "name": "Logic Shortcodes",
    "slug": "logic-shortcodes",
    "version": "1.0",
    "author": "<a href=\"http://www.samueldiethelm.com/\">Samuel Diethelm</a>",
    "author_profile": "https://profiles.wordpress.org/samueldiethelm/",
    "contributors": {
        "samueldiethelm": {
            "profile": "https://profiles.wordpress.org/samueldiethelm/",
            "avatar": "https://secure.gravatar.com/avatar/631c0568e1f97d70d5818a1ee1a701ef?s=96&d=monsterid&r=g",
            "display_name": "Samuel Diethelm"
        }
    },
    "requires": "2.5.0",
    "tested": "5.4.16",
    "requires_php": false,
    "requires_plugins": [],
    "compatibility": [],
    "rating": 0,
    "ratings": {
        "5": 0,
        "4": 0,
        "3": 0,
        "2": 0,
        "1": 0
    },
    "num_ratings": 0,
    "support_url": "https://wordpress.org/support/plugin/logic-shortcodes/",
    "support_threads": 0,
    "support_threads_resolved": 0,
    "active_installs": 10,
    "downloaded": 1049,
    "last_updated": "2016-04-28 7:12pm GMT",
    "added": "2016-04-19",
    "homepage": "https://wordpress.org/plugins/logic-shortcodes/",
    "sections": {
        "description": "<p>This plugin enables the use of [if] shortcodes to work with conditional logic based on the existence of post meta or taxonomy terms on posts and pages.</p>\n<p>Please consider taking a minute to rate the plugin or let me know any feature request. Thanks!</p>\n<h4>Taxonomy</h4>\n<p>With conditional logic for taxonomy terms, you can use names, slugs or term_ids:</p>\n<ul>\n<li>[if taxonomy=&#8221;category&#8221; slug=&#8221;cars&#8221;]Content to show[/if]</li>\n<li>[if taxonomy=&#8221;category&#8221; name=&#8221;Cars&#8221;]Content to show[/if]</li>\n<li>[if taxonomy=&#8221;category&#8221; id=&#8221;123&#8243;]Content to show[/if]</li>\n</ul>\n<h4>Post Meta</h4>\n<p>Post meta (or custom field) logic can be used to check if a certain meta_key AND meta_value combination are present or just a meta_key:</p>\n<ul>\n<li>[if postmeta=&#8221;car_model&#8221;]Content to show if car model info is present[/if]</li>\n<li>[if postmeta=&#8221;car_model&#8221; value=&#8221;Tesla Model S&#8221;]Content to show if car model is Tesla Model S[/if]</li>\n</ul>\n",
        "installation": "<ol>\n<li>Upload the plugin files to the <code>/wp-content/plugins/</code> directory, or install the plugin through the WordPress plugins screen directly.</li>\n<li>Activate the plugin through the &#8216;Plugins&#8217; screen in WordPress</li>\n</ol>\n",
        "faq": "\n<h4>Where can I use the logic?</h4>\n<p>\n<p>Anywhere where shortcodes are accepted and a post or page is being displayed.</p>\n</p>\n\n",
        "changelog": "<h4>1.0</h4>\n<ul>\n<li>Initial upload</li>\n</ul>\n"
    },
    "short_description": "Use shortcodes for conditional logic based on post meta or taxonomy terms.",
    "description": "<p>This plugin enables the use of [if] shortcodes to work with conditional logic based on the existence of post meta or taxonomy terms on posts and pages.</p>\n<p>Please consider taking a minute to rate the plugin or let me know any feature request. Thanks!</p>\n<h4>Taxonomy</h4>\n<p>With conditional logic for taxonomy terms, you can use names, slugs or term_ids:</p>\n<ul>\n<li>[if taxonomy=&#8221;category&#8221; slug=&#8221;cars&#8221;]Content to show[/if]</li>\n<li>[if taxonomy=&#8221;category&#8221; name=&#8221;Cars&#8221;]Content to show[/if]</li>\n<li>[if taxonomy=&#8221;category&#8221; id=&#8221;123&#8243;]Content to show[/if]</li>\n</ul>\n<h4>Post Meta</h4>\n<p>Post meta (or custom field) logic can be used to check if a certain meta_key AND meta_value combination are present or just a meta_key:</p>\n<ul>\n<li>[if postmeta=&#8221;car_model&#8221;]Content to show if car model info is present[/if]</li>\n<li>[if postmeta=&#8221;car_model&#8221; value=&#8221;Tesla Model S&#8221;]Content to show if car model is Tesla Model S[/if]</li>\n</ul>\n",
    "download_link": "https://downloads.wordpress.org/plugin/logic-shortcodes.zip",
    "upgrade_notice": [],
    "screenshots": [],
    "tags": {
        "conditional": "conditional",
        "logic": "logic",
        "postmeta": "postmeta",
        "taxonomy": "taxonomy",
        "term": "term"
    },
    "stable_tag": "trunk",
    "versions": [],
    "business_model": false,
    "repository_url": "",
    "commercial_support_url": "",
    "donate_link": "",
    "banners": [],
    "icons": {
        "default": "https://s.w.org/plugins/geopattern-icon/logic-shortcodes.svg"
    },
    "blocks": [],
    "block_assets": [],
    "author_block_count": 0,
    "author_block_rating": 0,
    "blueprints": [],
    "preview_link": "",
    "language_packs": []
}