{
    "name": "Vine MA &#8211; Email Marketing, Forms, Interactive Bot Forms, Chatbot, Analytics",
    "slug": "vine-ma",
    "version": "1.3.0",
    "author": "<a href=\"https://vine.eu\">Vine Oy</a>",
    "author_profile": "https://profiles.wordpress.org/vinema/",
    "contributors": {
        "vinema": {
            "profile": "https://profiles.wordpress.org/vinema/",
            "avatar": "https://secure.gravatar.com/avatar/5d36f8a6240277f58a4e799fb793615c?s=96&d=monsterid&r=g",
            "display_name": "vinema"
        }
    },
    "requires": "3.0.1",
    "tested": "6.6.1",
    "requires_php": "5.2",
    "requires_plugins": [],
    "compatibility": [],
    "rating": 0,
    "ratings": {
        "5": 0,
        "4": 0,
        "3": 0,
        "2": 0,
        "1": 0
    },
    "num_ratings": 0,
    "support_url": "https://wordpress.org/support/plugin/vine-ma/",
    "support_threads": 0,
    "support_threads_resolved": 0,
    "active_installs": 30,
    "downloaded": 1447,
    "last_updated": "2024-07-10 8:36am GMT",
    "added": "2020-07-10",
    "homepage": "",
    "sections": {
        "installation": "<h4>From your WordPress dashboard</h4>\n<ol>\n<li>Visit &#8216;Plugins &gt; Add New&#8217;</li>\n<li>Search for &#8216;vine&#8217;</li>\n<li>Activate Vine from your Plugins page</li>\n<li>Login by using MA account at the plugin settings page</li>\n</ol>\n",
        "faq": "\n<dt id='can%20i%20use%20the%20plugin%20without%20vine%20account'>\nCan I use the plugin without Vine account\n</h4>\n<p>\n<p>There is no option to use it without account</p>\n</p>\n\n",
        "changelog": "<h4>1.3.0</h4>\n<ul>\n<li>Use new script path /vscript/* instead of /track/*. Compatibility with WordPress 6.4</li>\n</ul>\n<h4>1.2.0</h4>\n<ul>\n<li>Use CDN also for the main script</li>\n</ul>\n<h4>1.1.7</h4>\n<ul>\n<li>Allow automatic script blocking for cookie consent</li>\n</ul>\n<h4>1.1.6</h4>\n<ul>\n<li>Avoid multiple organizations accounts to login</li>\n</ul>\n<h4>1.1.5</h4>\n<ul>\n<li>Fixed compatibility issue with DIVI editor</li>\n</ul>\n<h4>1.1.4</h4>\n<ul>\n<li>Support CookieBot automatically without any configuration</li>\n</ul>\n<h4>1.1.3</h4>\n<ul>\n<li>Support older WP versions</li>\n</ul>\n<h4>1.1.2</h4>\n<ul>\n<li>Bugfixing</li>\n</ul>\n<h4>1.1.1</h4>\n<ul>\n<li>Some bugfixing</li>\n</ul>\n<h4>1.1.0</h4>\n<ul>\n<li>MA Login added to plugin settings. Not necessary to enter the organization ID manually. </li>\n<li>Vine Web Form Gutenberg Block added to editor. Just insert the block and select a Vine Form.</li>\n</ul>\n<h4>1.0.0</h4>\n<ul>\n<li>Initial Public Release</li>\n</ul>\n",
        "description": "<p>Vine is a Marketing automation tool that helps you generate better leads from your web site visitors and gradually convert them into buying customers. It includes Web site visitor tracking , web forms (including interactive bot forms), landing pages, AI chatbot (including live chat) , email marketing, automated workflows, thorough analytics, and integration with Vine CRM or third party tools.</p>\n"
    },
    "short_description": "Vine is a Marketing automation tool that helps you generate better leads from your web site visitors and gradually convert them into buying customers.",
    "description": "<p>Vine is a Marketing automation tool that helps you generate better leads from your web site visitors and gradually convert them into buying customers. It includes Web site visitor tracking , web forms (including interactive bot forms), landing pages, AI chatbot (including live chat) , email marketing, automated workflows, thorough analytics, and integration with Vine CRM or third party tools.</p>\n",
    "download_link": "https://downloads.wordpress.org/plugin/vine-ma.zip",
    "upgrade_notice": {
        "1.1": "<p>MA Login added to plugin settings</p>",
        "1.0": "<p>Just released into the wild</p>"
    },
    "screenshots": [
        {
            "src": "https://ps.w.org/vine-ma/assets/screenshot-1.png?rev=2389533",
            "caption": "The plugin settings page"
        },
        {
            "src": "https://ps.w.org/vine-ma/assets/screenshot-2.png?rev=2338613",
            "caption": "Marketing Email Templates"
        },
        {
            "src": "https://ps.w.org/vine-ma/assets/screenshot-3.png?rev=2338613",
            "caption": "Registration Web Form"
        },
        {
            "src": "https://ps.w.org/vine-ma/assets/screenshot-4.png?rev=2338613",
            "caption": "Chatbot with Live Chat"
        },
        {
            "src": "https://ps.w.org/vine-ma/assets/screenshot-5.png?rev=2338613",
            "caption": "Metrics for Sent Email"
        },
        {
            "src": "https://ps.w.org/vine-ma/assets/screenshot-6.png?rev=2338613",
            "caption": "Interactive Bot Form"
        },
        {
            "src": "https://ps.w.org/vine-ma/assets/screenshot-7.png?rev=2338613",
            "caption": "Landing Page Usage Statistics"
        },
        {
            "src": "https://ps.w.org/vine-ma/assets/screenshot-8.png?rev=2338613",
            "caption": "Workflow Automation Diagram"
        },
        {
            "src": "https://ps.w.org/vine-ma/assets/screenshot-9.png?rev=2389533",
            "caption": "Vine Web Form Gutenberg Block"
        }
    ],
    "tags": {
        "automation": "automation",
        "email": "email",
        "marketing": "marketing",
        "vine": "vine",
        "visitor-tracking": "visitor tracking"
    },
    "stable_tag": "trunk",
    "versions": [],
    "business_model": false,
    "repository_url": "",
    "commercial_support_url": "",
    "donate_link": "",
    "banners": [],
    "icons": {
        "1x": "https://ps.w.org/vine-ma/assets/icon.svg?rev=2338548",
        "svg": "https://ps.w.org/vine-ma/assets/icon.svg?rev=2338548"
    },
    "blocks": {
        "vine-ma-plugin/vine-web-form": {
            "name": "vine-ma-plugin/vine-web-form",
            "title": "Vine: Web Form"
        }
    },
    "block_assets": [],
    "author_block_count": 1,
    "author_block_rating": 0,
    "blueprints": [],
    "preview_link": "",
    "language_packs": []
}