{
    "name": "Youtube Channel Plugin",
    "slug": "youtube-channel-showcase",
    "version": "0.2",
    "author": "Marc Rice",
    "author_profile": "https://profiles.wordpress.org/marcrice83/",
    "contributors": {
        "marcrice83": {
            "profile": "https://profiles.wordpress.org/marcrice83/",
            "avatar": "https://secure.gravatar.com/avatar/9b1fed964aca94a6241b5001f969876c?s=96&d=monsterid&r=g",
            "display_name": "marcrice83"
        }
    },
    "requires": "2.0.2",
    "tested": "1",
    "requires_php": false,
    "requires_plugins": [],
    "compatibility": [],
    "rating": 80,
    "ratings": {
        "5": 1,
        "4": 0,
        "3": 1,
        "2": 0,
        "1": 0
    },
    "num_ratings": 2,
    "support_url": "https://wordpress.org/support/plugin/youtube-channel-showcase/",
    "support_threads": 0,
    "support_threads_resolved": 0,
    "active_installs": 100,
    "downloaded": 21602,
    "last_updated": "2014-05-15 18:36:00",
    "added": "2011-11-23",
    "homepage": "http://www.github.com/marcrice83",
    "sections": {
        "description": "<p>Youtube channel gallery &#8211; displays list of youtube videos from a channel and showcases a selected video at the top which can be rotated</p>\n<h4>Recent Updates</h4>\n<p>Patch applied to improve the regex for selecting videos (thanks albertocm) &#8211; 12th Feb 2012</p>\n<h4>Limitations of this version</h4>\n<p>The following will require css to be created by the user<br />\nStyling the videos to have more than 1 on each line<br />\nResizing the showcase or thumbnails from the default size</p>\n<h4>Get in touch</h4>\n<p><a href=\"mailto:&#047;/&#x6d;&#x61;&#x72;&#x63;&#114;&#105;&#099;&#101;8&#x33;&#x40;&#x67;&#x6f;&#111;&#103;&#108;&#101;m&#x61;&#x69;&#x6c;&#x2e;&#099;&#111;&#109;&#047;\" title=\"developer email contact\" rel=\"nofollow ugc\">Email Me</a></p>\n<h4>Get in touch</h4>\n<p>Email me at marcrice83 at googlemail.com</p>\n",
        "installation": "<p>This section describes how to install the plugin and get it working:</p>\n<ol>\n<li>Download plugin and drop it into your plugins directory</li>\n<li>Activate the plugin through the &#8216;Plugins&#8217; menu in WordPress</li>\n<li>Place a shortcode in your page or post, for example: </li>\n</ol>\n<p>[ytchannel channel=&#8221;soccer&#8221; showcase=&#8221;gIHCVA54XnE&#8221; limit=&#8221;6&#8243; showcase_width=&#8221;630&#8243; thumbnail_width=&#8221;200&#8243;]</p>\n",
        "faq": "\n<h4>How do i get the videos to display more than 1 per row</h4>\n<p>\n<p>There are limited default styles for the plugin, you need to add your own css to set the display options for the list of videos</p>\n</p>\n\n",
        "changelog": "<h4>12th feb</h4>\n<p>added in a patch from github &#8211; provided by albertocm &#8211; better regex for setting video id</p>\n"
    },
    "short_description": "Youtube channel gallery - displays list of youtube videos from a channel and showcases a selected video at the top which can be rotated",
    "description": "<p>Youtube channel gallery &#8211; displays list of youtube videos from a channel and showcases a selected video at the top which can be rotated</p>\n<h4>Recent Updates</h4>\n<p>Patch applied to improve the regex for selecting videos (thanks albertocm) &#8211; 12th Feb 2012</p>\n<h4>Limitations of this version</h4>\n<p>The following will require css to be created by the user<br />\nStyling the videos to have more than 1 on each line<br />\nResizing the showcase or thumbnails from the default size</p>\n<h4>Get in touch</h4>\n<p><a href=\"mailto:&#047;/&#x6d;&#x61;&#x72;&#x63;&#114;&#105;&#099;&#101;8&#x33;&#x40;&#x67;&#x6f;&#111;&#103;&#108;&#101;m&#x61;&#x69;&#x6c;&#x2e;&#099;&#111;&#109;&#047;\" title=\"developer email contact\" rel=\"nofollow ugc\">Email Me</a></p>\n<h4>Get in touch</h4>\n<p>Email me at marcrice83 at googlemail.com</p>\n",
    "download_link": "https://downloads.wordpress.org/plugin/youtube-channel-showcase.zip",
    "upgrade_notice": [],
    "screenshots": [
        {
            "src": "https://ps.w.org/youtube-channel-showcase/trunk/screenshot-1.png?rev=1567048",
            "caption": "An example showcase output which has been styled with a 3 column layout for channel videos below the showcase video"
        }
    ],
    "tags": {
        "embed-youtube": "Embed youtube",
        "youtube": "youtube",
        "youtube-channel": "youtube channel",
        "youtube-gallery": "youtube gallery"
    },
    "stable_tag": "trunk",
    "versions": {
        "0.1": "https://downloads.wordpress.org/plugin/youtube-channel-showcase.0.1.zip",
        "1": "https://downloads.wordpress.org/plugin/youtube-channel-showcase.1.zip"
    },
    "business_model": false,
    "repository_url": "",
    "commercial_support_url": "",
    "donate_link": "",
    "banners": [],
    "icons": {
        "default": "https://s.w.org/plugins/geopattern-icon/youtube-channel-showcase.svg"
    },
    "blocks": [],
    "block_assets": [],
    "author_block_count": 0,
    "author_block_rating": 80,
    "blueprints": [],
    "preview_link": "",
    "language_packs": []
}